<?xml version="1.0" encoding="windows-1252" ?>
<!DOCTYPE Entity SYSTEM "jbo_03_01.dtd">
<!---->
<Entity
  xmlns="http://xmlns.oracle.com/bc4j"
  Name="XpeDccCfgCmtmntFacilityEO"
  Version="12.2.1.11.57"
  InheritPersonalization="merge"
  DBObjectType="table"
  DBObjectName="XPE_DCC_CFG_CMTMNT_FACILITY"
  AliasName="XpeDccCfgCmtmntFacilityEO"
  BindingStyle="OracleName">
  <Attribute
    Name="XpeFacilityId"
    IsNotNull="true"
    Precision="20"
    ColumnName="XPE_FACILITY_ID"
    SQLType="VARCHAR"
    Type="java.lang.String"
    ColumnType="VARCHAR2"
    TableName="XPE_DCC_CFG_CMTMNT_FACILITY"
    PrimaryKey="true">
    <DesignTime>
      <Attr Name="_DisplaySize" Value="20"/>
    </DesignTime>
  </Attribute>
  <Attribute
    Name="CustomerCareReview"
    Precision="100"
    ColumnName="CUSTOMER_CARE_REVIEW"
    SQLType="VARCHAR"
    Type="java.lang.String"
    ColumnType="VARCHAR2"
    TableName="XPE_DCC_CFG_CMTMNT_FACILITY">
    <DesignTime>
      <Attr Name="_DisplaySize" Value="100"/>
    </DesignTime>
  </Attribute>
  <Attribute
    Name="LegalReview"
    Precision="100"
    ColumnName="LEGAL_REVIEW"
    SQLType="VARCHAR"
    Type="java.lang.String"
    ColumnType="VARCHAR2"
    TableName="XPE_DCC_CFG_CMTMNT_FACILITY">
    <DesignTime>
      <Attr Name="_DisplaySize" Value="100"/>
    </DesignTime>
  </Attribute>
  <Attribute
    Name="FinancialReview"
    Precision="100"
    ColumnName="FINANCIAL_REVIEW"
    SQLType="VARCHAR"
    Type="java.lang.String"
    ColumnType="VARCHAR2"
    TableName="XPE_DCC_CFG_CMTMNT_FACILITY">
    <DesignTime>
      <Attr Name="_DisplaySize" Value="100"/>
    </DesignTime>
  </Attribute>
  <Attribute
    Name="GeneralManagerReview"
    Precision="100"
    ColumnName="GENERAL_MANAGER_REVIEW"
    SQLType="VARCHAR"
    Type="java.lang.String"
    ColumnType="VARCHAR2"
    TableName="XPE_DCC_CFG_CMTMNT_FACILITY">
    <DesignTime>
      <Attr Name="_DisplaySize" Value="100"/>
    </DesignTime>
  </Attribute>
  <Attribute
    Name="SustSolReview"
    Precision="100"
    ColumnName="SUST_SOL_REVIEW"
    SQLType="VARCHAR"
    Type="java.lang.String"
    ColumnType="VARCHAR2"
    TableName="XPE_DCC_CFG_CMTMNT_FACILITY">
    <DesignTime>
      <Attr Name="_DisplaySize" Value="100"/>
    </DesignTime>
  </Attribute>
  <Attribute
    Name="CfoReview"
    Precision="100"
    ColumnName="CFO_REVIEW"
    SQLType="VARCHAR"
    Type="java.lang.String"
    ColumnType="VARCHAR2"
    TableName="XPE_DCC_CFG_CMTMNT_FACILITY">
    <DesignTime>
      <Attr Name="_DisplaySize" Value="100"/>
    </DesignTime>
  </Attribute>
  <Attribute
    Name="CeoReview"
    Precision="100"
    ColumnName="CEO_REVIEW"
    SQLType="VARCHAR"
    Type="java.lang.String"
    ColumnType="VARCHAR2"
    TableName="XPE_DCC_CFG_CMTMNT_FACILITY">
    <DesignTime>
      <Attr Name="_DisplaySize" Value="100"/>
    </DesignTime>
  </Attribute>
  <Attribute
    Name="CreatedBy"
    Precision="15"
    Scale="0"
    ColumnName="CREATED_BY"
    SQLType="NUMERIC"
    Type="java.lang.Long"
    ColumnType="NUMBER"
    TableName="XPE_DCC_CFG_CMTMNT_FACILITY"/>
  <Attribute
    Name="CreationDate"
    ColumnName="CREATION_DATE"
    SQLType="DATE"
    Type="java.sql.Timestamp"
    ColumnType="DATE"
    TableName="XPE_DCC_CFG_CMTMNT_FACILITY"/>
  <Attribute
    Name="LastUpdatedBy"
    Precision="15"
    Scale="0"
    ColumnName="LAST_UPDATED_BY"
    SQLType="NUMERIC"
    Type="java.lang.Long"
    ColumnType="NUMBER"
    TableName="XPE_DCC_CFG_CMTMNT_FACILITY"/>
  <Attribute
    Name="LastUpdateDate"
    ColumnName="LAST_UPDATE_DATE"
    SQLType="DATE"
    Type="java.sql.Timestamp"
    ColumnType="DATE"
    TableName="XPE_DCC_CFG_CMTMNT_FACILITY"/>
  <Key
    Name="XpeCmtmntFacilityPk"
    PrimaryKey="true">
    <DesignTime>
      <Attr Name="_DBObjectName" Value="XPE_CMTMNT_FACILITY_PK"/>
    </DesignTime>
    <AttrArray Name="Attributes">
      <Item Value="model.entities.XpeDccCfgCmtmntFacilityEO.XpeFacilityId"/>
    </AttrArray>
  </Key>
</Entity>
